iso3166_updates/README.md
iso3166_updates/__init__.py
iso3166_updates/iso3166-updates.json
iso3166_updates/iso3166_updates.py
iso3166_updates-1.8.5.dist-info/LICENSE
iso3166_updates-1.8.5.dist-info/METADATA
iso3166_updates-1.8.5.dist-info/WHEEL
iso3166_updates-1.8.5.dist-info/RECORD
