Metadata-Version: 2.3
Name: iso3166-updates
Version: 1.8.5
Summary: Get the latest updates & changes to all ISO 3166 listed countries, dependent territories, and special areas of geographical interest.
License: MIT
Keywords: iso,iso3166,beautifulsoup,python,pypi,countries,country codes,csv,iso3166-2,subdivisions,iso3166-1,alpha-2,alpha-3,selenium,chromedriver
Author: AJ McKenna
Author-email: amckenna41@qub.ac.uk
Maintainer: AJ McKenna
Maintainer-email: amckenna41@qub.ac.uk
Requires-Python: >=3.9,<4.0
Classifier: Development Status :: 5 - Production/Stable
Classifier: Environment :: Console
Classifier: Intended Audience :: Developers
Classifier: Intended Audience :: Information Technology
Classifier: Intended Audience :: Science/Research
Classifier: License :: Free For Educational Use
Classifier: License :: OSI Approved :: MIT License
Classifier: Natural Language :: English
Classifier: Programming Language :: Python :: 3
Classifier: Programming Language :: Python :: 3.9
Classifier: Programming Language :: Python :: 3.10
Classifier: Programming Language :: Python :: 3.11
Classifier: Programming Language :: Python :: 3.12
Classifier: Programming Language :: Python :: 3.13
Classifier: Programming Language :: Python :: 3 :: Only
Classifier: Programming Language :: Python :: Implementation :: PyPy
Classifier: Topic :: Scientific/Engineering
Classifier: Topic :: Scientific/Engineering :: Information Analysis
Classifier: Topic :: Software Development :: Libraries :: Python Modules
Requires-Dist: iso3166 (>=2.1.1,<3.0.0)
Requires-Dist: python-dateutil (>=2.9.0.post0,<3.0.0)
Requires-Dist: thefuzz (>=0.22.1,<0.23.0)
Project-URL: documentation, https://iso3166-updates.readthedocs.io/en/latest/
Project-URL: homepage, https://iso3166-updates.com/api/
Project-URL: repository, https://github.com/amckenna41/iso3166-updates
